[
  {
    "data": {
      "id": "arn:aws:::802787198489:",
      "local_id": "802787198489",
      "name": "bb-apps-prd",
      "node_data": {},
      "type": "account"
    }
  },
  {
    "data": {
      "id": "arn:aws::us-east-1:802787198489:",
      "local_id": "us-east-1",
      "name": "us-east-1",
      "node_data": {},
      "parent": "arn:aws:::802787198489:",
      "type": "region"
    }
  },
  {
    "data": {
      "id": "arn:aws::us-east-1:802787198489:vpc/vpc-034938e8810b34937",
      "local_id": "vpc-034938e8810b34937",
      "name": "bb-apps-prd-vpc (172.18.64.0/20)",
      "node_data": {},
      "parent": "arn:aws::us-east-1:802787198489:",
      "type": "vpc"
    }
  },
  {
    "data": {
      "id": "arn:aws::us-east-1:802787198489:vpc/vpc-034938e8810b34937/az/us-east-1a",
      "local_id": "us-east-1a",
      "name": "us-east-1a",
      "node_data": {},
      "parent": "arn:aws::us-east-1:802787198489:vpc/vpc-034938e8810b34937",
      "type": "az"
    }
  },
  {
    "data": {
      "id": "arn:aws::us-east-1:802787198489:subnet/subnet-0cc2c8d5107af9c17",
      "local_id": "subnet-0cc2c8d5107af9c17",
      "name": "bb-apps-prd-vpc-private-us-east-1a (172.18.64.0/23)",
      "node_data": {},
      "parent": "arn:aws::us-east-1:802787198489:vpc/vpc-034938e8810b34937/az/us-east-1a",
      "type": "subnet"
    }
  },
  {
    "data": {
      "id": "arn:aws:ec2:us-east-1:802787198489:instance/i-015b8600a62ee002b",
      "local_id": "i-015b8600a62ee002b",
      "name": "ec2-fleet-1",
      "node_data": {},
      "parent": "arn:aws::us-east-1:802787198489:subnet/subnet-0cc2c8d5107af9c17",
      "type": "ec2"
    }
  },
  {
    "data": {
      "id": "arn:aws::us-east-1:802787198489:subnet/subnet-0168b79dbe8d21178",
      "local_id": "subnet-0168b79dbe8d21178",
      "name": "bb-apps-prd-vpc-public-us-east-1a (172.18.72.0/23)",
      "node_data": {},
      "parent": "arn:aws::us-east-1:802787198489:vpc/vpc-034938e8810b34937/az/us-east-1a",
      "type": "subnet"
    }
  },
  {
    "data": {
      "id": "arn:aws:ec2:us-east-1:802787198489:instance/i-08665ffb23eeee97f",
      "local_id": "i-08665ffb23eeee97f",
      "name": "ec2-fleet-4",
      "node_data": {},
      "parent": "arn:aws::us-east-1:802787198489:subnet/subnet-0168b79dbe8d21178",
      "type": "ec2"
    }
  },
  {
    "data": {
      "id": "arn:aws::us-east-1:802787198489:vpc/vpc-034938e8810b34937/az/us-east-1b",
      "local_id": "us-east-1b",
      "name": "us-east-1b",
      "node_data": {},
      "parent": "arn:aws::us-east-1:802787198489:vpc/vpc-034938e8810b34937",
      "type": "az"
    }
  },
  {
    "data": {
      "id": "arn:aws::us-east-1:802787198489:subnet/subnet-033a4d7f0f39254a1",
      "local_id": "subnet-033a4d7f0f39254a1",
      "name": "bb-apps-prd-vpc-private-us-east-1b (172.18.66.0/23)",
      "node_data": {},
      "parent": "arn:aws::us-east-1:802787198489:vpc/vpc-034938e8810b34937/az/us-east-1b",
      "type": "subnet"
    }
  },
  {
    "data": {
      "id": "arn:aws:ec2:us-east-1:802787198489:instance/i-02e92c3715cd2de8e",
      "local_id": "i-02e92c3715cd2de8e",
      "name": "ec2-fleet-2",
      "node_data": {},
      "parent": "arn:aws::us-east-1:802787198489:subnet/subnet-033a4d7f0f39254a1",
      "type": "ec2"
    }
  },
  {
    "data": {
      "id": "arn:aws::us-east-1:802787198489:subnet/subnet-0fde8d77478b9a38f",
      "local_id": "subnet-0fde8d77478b9a38f",
      "name": "bb-apps-prd-vpc-public-us-east-1b (172.18.74.0/23)",
      "node_data": {},
      "parent": "arn:aws::us-east-1:802787198489:vpc/vpc-034938e8810b34937/az/us-east-1b",
      "type": "subnet"
    }
  },
  {
    "data": {
      "id": "arn:aws:ec2:us-east-1:802787198489:instance/i-08ba7142fb2dc3f0d",
      "local_id": "i-08ba7142fb2dc3f0d",
      "name": "ec2-fleet-5",
      "node_data": {},
      "parent": "arn:aws::us-east-1:802787198489:subnet/subnet-0fde8d77478b9a38f",
      "type": "ec2"
    }
  },
  {
    "data": {
      "id": "arn:aws::us-east-1:802787198489:vpc/vpc-034938e8810b34937/az/us-east-1c",
      "local_id": "us-east-1c",
      "name": "us-east-1c",
      "node_data": {},
      "parent": "arn:aws::us-east-1:802787198489:vpc/vpc-034938e8810b34937",
      "type": "az"
    }
  },
  {
    "data": {
      "id": "arn:aws::us-east-1:802787198489:subnet/subnet-03ffba96c84433a5c",
      "local_id": "subnet-03ffba96c84433a5c",
      "name": "bb-apps-prd-vpc-public-us-east-1c (172.18.76.0/23)",
      "node_data": {},
      "parent": "arn:aws::us-east-1:802787198489:vpc/vpc-034938e8810b34937/az/us-east-1c",
      "type": "subnet"
    }
  },
  {
    "data": {
      "id": "arn:aws:ec2:us-east-1:802787198489:instance/i-08d3949af403bec83",
      "local_id": "i-08d3949af403bec83",
      "name": "ec2-fleet-6",
      "node_data": {},
      "parent": "arn:aws::us-east-1:802787198489:subnet/subnet-03ffba96c84433a5c",
      "type": "ec2"
    }
  },
  {
    "data": {
      "id": "arn:aws::us-east-1:802787198489:subnet/subnet-0599bfa8d84dc6d2c",
      "local_id": "subnet-0599bfa8d84dc6d2c",
      "name": "bb-apps-prd-vpc-private-us-east-1c (172.18.68.0/23)",
      "node_data": {},
      "parent": "arn:aws::us-east-1:802787198489:vpc/vpc-034938e8810b34937/az/us-east-1c",
      "type": "subnet"
    }
  },
  {
    "data": {
      "id": "arn:aws:ec2:us-east-1:802787198489:instance/i-04b74e57379c1b8c1",
      "local_id": "i-04b74e57379c1b8c1",
      "name": "ec2-fleet-3",
      "node_data": {},
      "parent": "arn:aws::us-east-1:802787198489:subnet/subnet-0599bfa8d84dc6d2c",
      "type": "ec2"
    }
  },
  {
    "data": {
      "node_data": {},
      "source": "arn:aws:ec2:us-east-1:802787198489:instance/i-015b8600a62ee002b",
      "target": "arn:aws:ec2:us-east-1:802787198489:instance/i-08665ffb23eeee97f",
      "type": "edge"
    }
  },
  {
    "data": {
      "node_data": {},
      "source": "arn:aws:ec2:us-east-1:802787198489:instance/i-015b8600a62ee002b",
      "target": "arn:aws:ec2:us-east-1:802787198489:instance/i-02e92c3715cd2de8e",
      "type": "edge"
    }
  },
  {
    "data": {
      "node_data": {},
      "source": "arn:aws:ec2:us-east-1:802787198489:instance/i-015b8600a62ee002b",
      "target": "arn:aws:ec2:us-east-1:802787198489:instance/i-08ba7142fb2dc3f0d",
      "type": "edge"
    }
  },
  {
    "data": {
      "node_data": {},
      "source": "arn:aws:ec2:us-east-1:802787198489:instance/i-015b8600a62ee002b",
      "target": "arn:aws:ec2:us-east-1:802787198489:instance/i-08d3949af403bec83",
      "type": "edge"
    }
  },
  {
    "data": {
      "node_data": {},
      "source": "arn:aws:ec2:us-east-1:802787198489:instance/i-015b8600a62ee002b",
      "target": "arn:aws:ec2:us-east-1:802787198489:instance/i-04b74e57379c1b8c1",
      "type": "edge"
    }
  },
  {
    "data": {
      "node_data": {},
      "source": "arn:aws:ec2:us-east-1:802787198489:instance/i-08665ffb23eeee97f",
      "target": "arn:aws:ec2:us-east-1:802787198489:instance/i-015b8600a62ee002b",
      "type": "edge"
    }
  },
  {
    "data": {
      "node_data": {},
      "source": "arn:aws:ec2:us-east-1:802787198489:instance/i-08665ffb23eeee97f",
      "target": "arn:aws:ec2:us-east-1:802787198489:instance/i-02e92c3715cd2de8e",
      "type": "edge"
    }
  },
  {
    "data": {
      "node_data": {},
      "source": "arn:aws:ec2:us-east-1:802787198489:instance/i-08665ffb23eeee97f",
      "target": "arn:aws:ec2:us-east-1:802787198489:instance/i-08ba7142fb2dc3f0d",
      "type": "edge"
    }
  },
  {
    "data": {
      "node_data": {},
      "source": "arn:aws:ec2:us-east-1:802787198489:instance/i-08665ffb23eeee97f",
      "target": "arn:aws:ec2:us-east-1:802787198489:instance/i-08d3949af403bec83",
      "type": "edge"
    }
  },
  {
    "data": {
      "node_data": {},
      "source": "arn:aws:ec2:us-east-1:802787198489:instance/i-08665ffb23eeee97f",
      "target": "arn:aws:ec2:us-east-1:802787198489:instance/i-04b74e57379c1b8c1",
      "type": "edge"
    }
  },
  {
    "data": {
      "node_data": {},
      "source": "arn:aws:ec2:us-east-1:802787198489:instance/i-02e92c3715cd2de8e",
      "target": "arn:aws:ec2:us-east-1:802787198489:instance/i-015b8600a62ee002b",
      "type": "edge"
    }
  },
  {
    "data": {
      "node_data": {},
      "source": "arn:aws:ec2:us-east-1:802787198489:instance/i-02e92c3715cd2de8e",
      "target": "arn:aws:ec2:us-east-1:802787198489:instance/i-08665ffb23eeee97f",
      "type": "edge"
    }
  },
  {
    "data": {
      "node_data": {},
      "source": "arn:aws:ec2:us-east-1:802787198489:instance/i-02e92c3715cd2de8e",
      "target": "arn:aws:ec2:us-east-1:802787198489:instance/i-08ba7142fb2dc3f0d",
      "type": "edge"
    }
  },
  {
    "data": {
      "node_data": {},
      "source": "arn:aws:ec2:us-east-1:802787198489:instance/i-02e92c3715cd2de8e",
      "target": "arn:aws:ec2:us-east-1:802787198489:instance/i-08d3949af403bec83",
      "type": "edge"
    }
  },
  {
    "data": {
      "node_data": {},
      "source": "arn:aws:ec2:us-east-1:802787198489:instance/i-02e92c3715cd2de8e",
      "target": "arn:aws:ec2:us-east-1:802787198489:instance/i-04b74e57379c1b8c1",
      "type": "edge"
    }
  },
  {
    "data": {
      "node_data": {},
      "source": "arn:aws:ec2:us-east-1:802787198489:instance/i-08ba7142fb2dc3f0d",
      "target": "arn:aws:ec2:us-east-1:802787198489:instance/i-015b8600a62ee002b",
      "type": "edge"
    }
  },
  {
    "data": {
      "node_data": {},
      "source": "arn:aws:ec2:us-east-1:802787198489:instance/i-08ba7142fb2dc3f0d",
      "target": "arn:aws:ec2:us-east-1:802787198489:instance/i-08665ffb23eeee97f",
      "type": "edge"
    }
  },
  {
    "data": {
      "node_data": {},
      "source": "arn:aws:ec2:us-east-1:802787198489:instance/i-08ba7142fb2dc3f0d",
      "target": "arn:aws:ec2:us-east-1:802787198489:instance/i-02e92c3715cd2de8e",
      "type": "edge"
    }
  },
  {
    "data": {
      "node_data": {},
      "source": "arn:aws:ec2:us-east-1:802787198489:instance/i-08ba7142fb2dc3f0d",
      "target": "arn:aws:ec2:us-east-1:802787198489:instance/i-08d3949af403bec83",
      "type": "edge"
    }
  },
  {
    "data": {
      "node_data": {},
      "source": "arn:aws:ec2:us-east-1:802787198489:instance/i-08ba7142fb2dc3f0d",
      "target": "arn:aws:ec2:us-east-1:802787198489:instance/i-04b74e57379c1b8c1",
      "type": "edge"
    }
  },
  {
    "data": {
      "node_data": {},
      "source": "arn:aws:ec2:us-east-1:802787198489:instance/i-08d3949af403bec83",
      "target": "arn:aws:ec2:us-east-1:802787198489:instance/i-015b8600a62ee002b",
      "type": "edge"
    }
  },
  {
    "data": {
      "node_data": {},
      "source": "arn:aws:ec2:us-east-1:802787198489:instance/i-08d3949af403bec83",
      "target": "arn:aws:ec2:us-east-1:802787198489:instance/i-08665ffb23eeee97f",
      "type": "edge"
    }
  },
  {
    "data": {
      "node_data": {},
      "source": "arn:aws:ec2:us-east-1:802787198489:instance/i-08d3949af403bec83",
      "target": "arn:aws:ec2:us-east-1:802787198489:instance/i-02e92c3715cd2de8e",
      "type": "edge"
    }
  },
  {
    "data": {
      "node_data": {},
      "source": "arn:aws:ec2:us-east-1:802787198489:instance/i-08d3949af403bec83",
      "target": "arn:aws:ec2:us-east-1:802787198489:instance/i-08ba7142fb2dc3f0d",
      "type": "edge"
    }
  },
  {
    "data": {
      "node_data": {},
      "source": "arn:aws:ec2:us-east-1:802787198489:instance/i-08d3949af403bec83",
      "target": "arn:aws:ec2:us-east-1:802787198489:instance/i-04b74e57379c1b8c1",
      "type": "edge"
    }
  },
  {
    "data": {
      "node_data": {},
      "source": "arn:aws:ec2:us-east-1:802787198489:instance/i-04b74e57379c1b8c1",
      "target": "arn:aws:ec2:us-east-1:802787198489:instance/i-015b8600a62ee002b",
      "type": "edge"
    }
  },
  {
    "data": {
      "node_data": {},
      "source": "arn:aws:ec2:us-east-1:802787198489:instance/i-04b74e57379c1b8c1",
      "target": "arn:aws:ec2:us-east-1:802787198489:instance/i-08665ffb23eeee97f",
      "type": "edge"
    }
  },
  {
    "data": {
      "node_data": {},
      "source": "arn:aws:ec2:us-east-1:802787198489:instance/i-04b74e57379c1b8c1",
      "target": "arn:aws:ec2:us-east-1:802787198489:instance/i-02e92c3715cd2de8e",
      "type": "edge"
    }
  },
  {
    "data": {
      "node_data": {},
      "source": "arn:aws:ec2:us-east-1:802787198489:instance/i-04b74e57379c1b8c1",
      "target": "arn:aws:ec2:us-east-1:802787198489:instance/i-08ba7142fb2dc3f0d",
      "type": "edge"
    }
  },
  {
    "data": {
      "node_data": {},
      "source": "arn:aws:ec2:us-east-1:802787198489:instance/i-04b74e57379c1b8c1",
      "target": "arn:aws:ec2:us-east-1:802787198489:instance/i-08d3949af403bec83",
      "type": "edge"
    }
  }
]
